{"version":1,"resource":"vscode-remote://970-cs-634126139426-default.cs-us-east1-rtep.cloudshell.dev/home/leozhontai561/main.py","entries":[{"id":"Z1Ja.py","timestamp":1739143529874},{"id":"2APE.py","source":"undoRedo.source","timestamp":1739143745130},{"id":"pd7J.py","timestamp":1739143854232},{"id":"sCBa.py","timestamp":1739144506261},{"id":"yftC.py","timestamp":1739144635880},{"id":"0ZwO.py","timestamp":1739144925775},{"id":"qf9l.py","timestamp":1739145101417},{"id":"smBe.py","source":"undoRedo.source","timestamp":1739145267679},{"id":"thTt.py","timestamp":1739145429024},{"id":"BQDp.py","source":"undoRedo.source","timestamp":1739145726820},{"id":"RJIW.py","timestamp":1739145808606},{"id":"p47I.py","timestamp":1739145980586},{"id":"JIeD.py","timestamp":1739146169971}]}